Metadata-Version: 2.4
Name: emuflash
Version: 10.0
Summary: A lightweight retro emulator featuring over 250 fully patched games, designed for effortless play with no PC-specific configuration required.
Home-page: https://github.com/royhtml
Author: Dwi Bakti N Dev
Author-email: dwibakti76@gmail.com
Project-URL: Profile, https://profiledwibaktindev.netlify.app/
Project-URL: ich.io, https://royhtml.itch.io/
Project-URL: Facebook, https://www.facebook.com/Royhtml
Project-URL: Webtoons, https://www.webtoons.com/id/canvas/mariadb-hari-senin/episode-4-coding-championship/viewer?title_no=1065164&episode_no=4
Classifier: Programming Language :: Python :: 3
Classifier: License :: OSI Approved :: MIT License
Classifier: Operating System :: OS Independent
Classifier: Topic :: Games/Entertainment
Classifier: Topic :: Games/Entertainment :: Arcade
Classifier: Topic :: Multimedia :: Graphics
Classifier: Intended Audience :: End Users/Desktop
Requires-Python: >=3.6
License-File: LICENSE.txt
Requires-Dist: pillow>=8.0
Requires-Dist: pyinstaller>=4.0
Requires-Dist: pyqt5>=5.15
Dynamic: author
Dynamic: author-email
Dynamic: classifier
Dynamic: description
Dynamic: description-content-type
Dynamic: home-page
Dynamic: license-file
Dynamic: project-url
Dynamic: requires-dist
Dynamic: requires-python
Dynamic: summary
